Metadata-Version: 2.1
Name: tokenwiser
Version: 0.1.7
Summary: UNKNOWN
Home-page: UNKNOWN
License: UNKNOWN
Platform: UNKNOWN
Requires-Dist: PyYAML (>=5.3.1)
Requires-Dist: Pyphen (>=0.10.0)
Requires-Dist: jellyfish (>=0.8.2)
Requires-Dist: scikit-learn (>=0.24.0)
Requires-Dist: sentencepiece (>=0.1.95)
Requires-Dist: snowballstemmer (>=2.1.0)
Requires-Dist: spacy (>=3.1.0)
Requires-Dist: vowpalwabbit (>=8.9.0)
Requires-Dist: yake-github (>=0.4.0)
Provides-Extra: dev
Requires-Dist: flake8 (>=3.6.0) ; extra == 'dev'
Requires-Dist: jupyter (>=1.0.0) ; extra == 'dev'
Requires-Dist: jupyterlab (>=0.35.4) ; extra == 'dev'
Requires-Dist: mkdocs-material (>=6.2.8) ; extra == 'dev'
Requires-Dist: mkdocs (>=1.1.2) ; extra == 'dev'
Requires-Dist: mkdocstrings (>=0.14.0) ; extra == 'dev'
Requires-Dist: mktestdocs (>=0.1.0) ; extra == 'dev'
Requires-Dist: pytest (>=4.0.2) ; extra == 'dev'
Provides-Extra: docs
Requires-Dist: mkdocs-material (>=6.2.8) ; extra == 'docs'
Requires-Dist: mkdocs (>=1.1.2) ; extra == 'docs'
Requires-Dist: mkdocstrings (>=0.14.0) ; extra == 'docs'
